autonomous_proto/__init__.py
autonomous_proto/autonomous_proto.py
autonomous_proto-0.1.4.dist-info/METADATA
autonomous_proto-0.1.4.dist-info/WHEEL
autonomous_proto-0.1.4.dist-info/RECORD
