Metadata-Version: 2.3
Name: autonomous_proto
Version: 0.1.4
Summary: autonomous_proto
Author-email: todo <todo@todo.com>
Requires-Python: >=3.9
Requires-Dist: betterproto[compiler]>=1.2.5
Requires-Dist: grpcio-tools>=1.68.1
Requires-Dist: stringcase>=1.2.0
